libphotospline.so
libphotospline.so.2.1.0
libphotospline.so.2
libdelabella.so
libcphotospline.so
libcphotospline.so.2
libcphotospline.so.2.1.0
lib/cmake/NamedTypeConfig.cmake
lib/cmake/NamedTypeConfigVersion.cmake
lib/cmake/NamedTypeTargets.cmake
siren/__init__.py
siren/geometry.cpython-39-aarch64-linux-gnu.so
siren/detector.cpython-39-aarch64-linux-gnu.so
siren/distributions.cpython-39-aarch64-linux-gnu.so
siren/interactions.cpython-39-aarch64-linux-gnu.so
siren/SIREN_DarkNews.py
siren/dataclasses.cpython-39-aarch64-linux-gnu.so
siren/math.cpython-39-aarch64-linux-gnu.so
siren/_util.py
siren/utilities.cpython-39-aarch64-linux-gnu.so
siren/injection.cpython-39-aarch64-linux-gnu.so
siren/SIREN_Controller.py
siren/DNModelContainer.py
siren/resources/Fluxes/BNB/BNB-v1.0/BNB_RHC.dat
siren/resources/Fluxes/BNB/BNB-v1.0/BNB_FHC.dat
siren/resources/Fluxes/BNB/BNB-v1.0/FluxCalculator.py
siren/resources/Fluxes/NUMI/NUMI-v1.0/NUMI_RHC_ME_unofficial.dat
siren/resources/Fluxes/NUMI/NUMI-v1.0/NUMI_FHC_ME.dat
siren/resources/Fluxes/NUMI/NUMI-v1.0/NUMI_RHC_ME.dat
siren/resources/Fluxes/NUMI/NUMI-v1.0/NUMI_RHC_LE.dat
siren/resources/Fluxes/NUMI/NUMI-v1.0/NUMI_FHC_LE.dat
siren/resources/Fluxes/NUMI/NUMI-v1.0/FluxCalculator.py
siren/resources/Fluxes/NUMI/NUMI-v1.0/NUMI_FHC_ME_unofficial.dat
siren/resources/Fluxes/HE_SN/HE_SN-v1.0/dN_dE_SNe_2n_D1_0_s20_t100d_NuMu_d10kpc.txt
siren/resources/Fluxes/HE_SN/HE_SN-v1.0/FluxCalculator.py
siren/resources/CrossSections/CSMSDISSplines/CSMSDISSplines-v1.0/sigma_nu_CC_iso.fits
siren/resources/CrossSections/CSMSDISSplines/CSMSDISSplines-v1.0/sigma_nu_NC_iso.fits
siren/resources/CrossSections/CSMSDISSplines/CSMSDISSplines-v1.0/dsdxdy_nu_NC_iso.fits
siren/resources/CrossSections/CSMSDISSplines/CSMSDISSplines-v1.0/dsdxdy_nubar_CC_iso.fits
siren/resources/CrossSections/CSMSDISSplines/CSMSDISSplines-v1.0/sigma_nubar_NC_iso.fits
siren-0.0.3.dist-info/WHEEL
siren-0.0.3.dist-info/RECORD
siren-0.0.3.dist-info/METADATA
siren-0.0.3.dist-info/licenses/LICENSE
