Metadata-Version: 2.1
Name: siren
Version: 0.0.3
Summary: Sampling and Injection for Rare EveNts: A neutrino and rare-process injection toolkit
Keywords: physics,hep,netrino,bsm,simulation,injection,weighting
Author-Email: Austin Schneider <aschn@mit.edu>, Nicholas Kamp <nkamp@fas.harvard.edu>
Maintainer-Email: Austin Schneider <aschn@mit.edu>, Nicholas Kamp <nkamp@fas.harvard.edu>
License:                    GNU LESSER GENERAL PUBLIC LICENSE
Classifier: Development Status :: 4 - Beta
Classifier: Intended Audience :: Science/Research
Classifier: Intended Audience :: Developers
Classifier: License :: OSI Approved :: GNU Lesser General Public License v3 (LGPLv3)
Classifier: Programming Language :: C++
Classifier: Programming Language :: Python :: 3
Classifier: Programming Language :: Python :: 3.8
Classifier: Programming Language :: Python :: 3.9
Classifier: Programming Language :: Python :: 3.10
Classifier: Programming Language :: Python :: 3.11
Classifier: Programming Language :: Python :: 3.12
Classifier: Programming Language :: Python :: 3 :: Only
Classifier: Operating System :: POSIX
Classifier: Operating System :: Unix
Classifier: Operating System :: MacOS
Classifier: Topic :: Scientific/Engineering :: Physics
Project-URL: Homepage, https://github.com/Harvard-Neutrino/SIREN
Project-URL: Documentation, https://readthedocs.org
Project-URL: Repository, https://github.com/Harvard-Neutrino/SIREN.git
Project-URL: Issues, https://github.com/Harvard-Neutrino/LeptonInjector/issues
Requires-Python: >=3.8
Requires-Dist: numpy
Requires-Dist: scipy
Requires-Dist: awkward
Requires-Dist: pyarrow
Requires-Dist: h5py
Requires-Dist: DarkNews>=0.4.2; extra == "darknews"
Provides-Extra: darknews
